{
    "part1" : [
        {
            "name" : "Toca Life: World",
            "screen" : "https://i.pinimg.com/564x/a8/6a/5c/a86a5ce4d13fb835dfe5ad07c8100aa2.jpg",
            "description" : "desc 1"
        },
        {
            "name" : "Toca Life: World",
            "screen" : "https://i.pinimg.com/564x/a8/6a/5c/a86a5ce4d13fb835dfe5ad07c8100aa2.jpg",
            "description" : "desc 2"
        },
        {
            "name" : "Toca Life: World",
            "screen" : "https://i.pinimg.com/564x/a8/6a/5c/a86a5ce4d13fb835dfe5ad07c8100aa2.jpg",
            "description" : "desc 3"
        },
        {
            "name" : "Toca Life: World",
            "screen" : "https://i.pinimg.com/564x/a8/6a/5c/a86a5ce4d13fb835dfe5ad07c8100aa2.jpg",
            "description" : "desc 4"
        }
    ],
    "part2" : [
        {
            "name" : "Toca Life: World",
            "screen" : "https://i.pinimg.com/564x/a8/6a/5c/a86a5ce4d13fb835dfe5ad07c8100aa2.jpg",
            "description" : "desc 1"
        },
        {
            "name" : "Toca Life: World",
            "screen" : "https://i.pinimg.com/564x/a8/6a/5c/a86a5ce4d13fb835dfe5ad07c8100aa2.jpg",
            "description" : "desc 1"
        }
    ],
    "part3" : [
        {
            "name" : "Toca Life: World",
            "screen" : "https://i.pinimg.com/564x/a8/6a/5c/a86a5ce4d13fb835dfe5ad07c8100aa2.jpg",
            "description" : "desc 1"
        },
        {
            "name" : "Toca Life: World",
            "screen" : "https://i.pinimg.com/564x/a8/6a/5c/a86a5ce4d13fb835dfe5ad07c8100aa2.jpg",
            "description" : "desc 1"
        },
        {
            "name" : "Toca Life: World",
            "screen" : "https://i.pinimg.com/564x/a8/6a/5c/a86a5ce4d13fb835dfe5ad07c8100aa2.jpg",
            "description" : "desc 1"
        }
    ]
}
